compiled_distributions/Binomialdistribution.py
compiled_distributions/Gaussiandistribution.py
compiled_distributions/Generaldistribution.py
compiled_distributions/__init__.py
compiled_distributions-0.1.dist-info/DESCRIPTION.rst
compiled_distributions-0.1.dist-info/METADATA
compiled_distributions-0.1.dist-info/RECORD
compiled_distributions-0.1.dist-info/WHEEL
compiled_distributions-0.1.dist-info/metadata.json
compiled_distributions-0.1.dist-info/top_level.txt
