Metadata-Version: 2.0
Name: compiled-distributions
Version: 0.1
Summary: Binomial and Gaussian distributions
Home-page: UNKNOWN
Author: LEE Hong Kai
Author-email: leehongkai@gmail.com
License: UNKNOWN
Platform: UNKNOWN
